README.md
setup.cfg
setup.py
repocache/__init__.py
repocache/main.py
repocache/maven.py
repocache/modular_view.py
repocache/npm.py
repocache/pypi.py
repocache/pypi_test.py
repocache/rust.py
repocache/server.py
repocache/vendor.py
repocache/yum.py
repocache.egg-info/PKG-INFO
repocache.egg-info/SOURCES.txt
repocache.egg-info/dependency_links.txt
repocache.egg-info/requires.txt
repocache.egg-info/top_level.txt
repocache/templates/index.html
repocache/templates/pypi/file_list.html
repocache/templates/yum/centos.repo
repocache/templates/yum/sclo.repo