Metadata-Version: 2.1
Name: repocache
Version: 0.3.3
Summary: Universal caching and proxying server for pypi/maven/npm/yum
Home-page: https://github.com/pedia/repocache
Author: repocache author
License: UNKNOWN
Platform: UNKNOWN
Classifier: Programming Language :: Python :: 3
Classifier: License :: OSI Approved :: MIT License
Classifier: Operating System :: OS Independent
